validata/__init__.py
validata/checker.py
validata/rules.py
validata/advanced_rules/__init__.py
validata/advanced_rules/integrity.py
validata/advanced_rules/semantic.py
validata/advanced_rules/statistical.py
validata/advanced_rules/time_series.py
datax_validator-0.1.3.dist-info/METADATA
datax_validator-0.1.3.dist-info/WHEEL
datax_validator-0.1.3.dist-info/top_level.txt
datax_validator-0.1.3.dist-info/RECORD
