Metadata-Version: 2.4
Name: datax-validator
Version: 0.1.3
Summary: A simple data quality checking package
Author: Ankita Singh
Project-URL: Homepage, https://github.com/ankitajaiwar/Validata
Project-URL: Bug Tracker, https://github.com/ankitajaiwar/Validata/issues
Requires-Python: >=3.8
Provides-Extra: dev
Requires-Dist: pytest; extra == "dev"
